{
  "key1": "Wert für key1 geändert",
  "key2": "Wert für key2 More ändern:",
  "key3": "Vater &  #8217s Geburtsort 30.12.2014 3: 13:00",
  "key4": "<span data-test='paginationStart'>{firstRecordIndex}</span>-<span data-test='paginationEnd'>{lastRecordIndex}</span> von <span data-test='totalResults'>{totalRecordCount}</span>",
  "key5": "Export der Ergebnisse {numberRange} 30.12.2014 2: 55 pm",
  "will": "Rufen Again:",
  "array1": {
    "parents": "Eltern",
    "father": "Vater",
    "mother": "Mutter"
  },
  "array2": {
    "aunt": "Tante 30.12.2014 3: 13:00",
    "brother": "Bruder",
    "sister": "Schwester",
    "cousin": "Nur Cousinen 2-Änderungen cousinKey"
  }
}